{
  	"type": "NTP",
	"rules": [
	  	{
		  	"name": "List NTP",
		  	"method": "list"
		},
	  	{
			"name": "Create NTP",
			"method": "create",
			"base": {
				"symbol": {
					"name": "NAS",
					"terminal": true
				}
			},
			"left": {
				"symbol": {
					"name": "*",
					"terminal": false,
					"symbol": {
						"name": "NTP",
						"terminal": false
					}
				}
			},
			"right": {
				"symbol": {
					"name": "*",
					"terminal": false,
					"symbol": {
						"name": "NTP",
						"terminal": true
					}
				}
			}
		},
		{
			"name": "Modify NTP",
			"method": "modify",
			"left": {
				"symbol": {
					"name": "*",
					"terminal": false,
					"symbol": {
						"name": "NTP",
						"terminal": true
					}
				}
			},
			"right": {
				"symbol": {
					"name": "*",
					"terminal": false,
					"symbol": {
						"name": "NTP",
						"terminal": true
					}
				}
			}
		},
		{
			"name": "Delete NTP",
			"method": "delete",
			"left": {
				"symbol": {
					"name": "*",
					"terminal": false,
					"symbol": {
						"name": "NTP",
						"terminal": true
					}
				}
			},
			"right": {
				"symbol": {
					"name": "*",
					"terminal": false,
					"symbol": {
						"name": "NTP",
						"terminal": false
					}
				}
			}
		}
	]
}